catchment/__init__.py
catchment-0.0.1.dist-info/METADATA
catchment-0.0.1.dist-info/WHEEL
catchment-0.0.1.dist-info/top_level.txt
catchment-0.0.1.dist-info/RECORD
