Metadata-Version: 2.1
Name: catchment
Version: 0.0.1
Summary: A python package for catchment delineation
Home-page: https://github.com/xiejx5/catchment
Author: Cody James
Author-email: xiejx5@gmail.com
License: MIT
Platform: UNKNOWN
Classifier: License :: OSI Approved :: MIT License
Classifier: Programming Language :: Python
Classifier: Programming Language :: Python :: 3
Classifier: Programming Language :: Python :: 3.7
Classifier: Programming Language :: Python :: Implementation :: CPython
Classifier: Programming Language :: Python :: Implementation :: PyPy
Requires-Python: ==3.7.*
Requires-Dist: numpy
Requires-Dist: numexpr
Requires-Dist: openpyxl
Requires-Dist: h5py
Requires-Dist: hdf5plugin
Requires-Dist: psutil
Requires-Dist: fileloc
Requires-Dist: gdal
Provides-Extra: fancy_feature
Requires-Dist: requests ; extra == 'fancy_feature'
Requires-Dist: six ; extra == 'fancy_feature'
Requires-Dist: jinja2 ; extra == 'fancy_feature'
Requires-Dist: pandas ; extra == 'fancy_feature'
